Workbook

Sheet Model Overview and Valuation Su
A2: Transaction Snapshot | B2: Values
A3: Acquirer | B3: Waste Management, Inc.
A4: Target | B4: Advanced Disposal Services
A5: Transaction Type | B5: Strategic Acquisition
A6: Sector | B6: Environmental Services
A7: Currency | B7: USD (mm)
A9: Key Valuation Assumptions
A10: Key Valuation Assumptions | B10: Value
A11: WACC | B11: 0.0655
A12: Terminal Growth Rate | B12: 0.0225
A13: Explicit Forecast Period | B13: 5 Years
A14: Valuation Methods | B14: DCF / Trading Comps / Precedents
A18: Implied Equity Value per Share — Advanced Disposal
A19: Valuation Method | B19: Value / Share
A20: DCF (Intrinsic Value) | B20: 89
A21: Trading Comps (Public Market) | B21: $51.4 – $65.5
A22: Precedent Transactions (Control) | B22: $55.2 – $69.2
A23: Offer Price (WM Acquisition) | B23: 30.3
A25: INVESTMENT VIEW
A26: • DCF analysis implies intrinsic value above public trading levels, supported by stable cash flows and asset-backed operations.
A27: • Public market and precedent transaction multiples provide valuation support within a reasonable control premium range.
A28: • Acquisition rationale supported by strategic fit, operating synergies, and long-term cash flow visibility.

Sheet Key Assumptions& MOdel Controls
A3: Operating Assumptions | B3: Values
A5: Revenue Growth (CGAR) | B5: 0.045
A6: EBITDA Margin | B6: 28-28.5%
A7: D&A % of Revenue | B7: 0.1
A8: CapEx % of Revenue | B8: 14-14.5%
A9: Change in NWC % of Revenue | B9: 0.005
A13: Valuation Assumptions | B13: Column1
A14: WAAC | B14: 0.0655
A15: Terminal Growth Rate
A16: Projection Period | B16: 5 Years
A17: Terminal Value Method | B17: Prepetuity Growth
A20: Capital Structure and Share Data | B20: Values
A21: Net Debt | B21: 16200
A22: Diluted Shares Outstanding | B22: 407
A23: Equity Value (DCF) | B23: 36232.4
A25: Model Controls | B25: Values
A26: Currency | B26: USD mm
A27: Fisical Year Convention | B27: 2023A
A28: Inflated embedded | B28: Yes
A29: Model Type | B29: Stadalone Valuation
A30: Sensitivity Method | B30: WACC x Terminal Growth

Sheet Operating Projections
A3: ($mm) | B3: 2023A (Base) | C3: 2024E (Y1) | D3: 2025E (Y2) | E3: 2026E (Y3) | F3: 2027E (Y4) | G3: 2028E (Y5)
A4: Revenue | B4: 20426 | C4: =B5*B4+B4 -> 21406.448 | D4: =C5*C4+C4 -> 22433.958 | E4: =D5*D4+D4 -> 23510.787 | F4: =E5*E4+E4 -> 24545.262 | G4: =F5*F4+F4 -> 25527.073
A5: YoY Growth | B5: 0.048 | C5: 0.048 | D5: 0.048 | E5: 0.044 | F5: 0.04 | G5: 0.038
A6: EBITDA | B6: 5891 | C6: =C7*C4 -> 5993.8054 | D6: =D7*D4 -> 6326.376 | E6: =E7*E4 -> 6677.0636 | F6: =F7*F4 -> 6995.3997 | G6: =G7*G4 -> 7275.2157
A7: EBITDA Margin | B7: 0.288 | C7: 0.28 | D7: 0.282 | E7: 0.284 | F7: 0.285 | G7: 0.285
A10: Revenue CGAR | B10: 0.0456
A11: EBITDA CGAR | B11: 0.0431
A12: EBITDA Margin Range | B12: 28%-28.5%

Sheet Unleveraged Cash Flow
A3: Metrics | B3: 2023A | C3: 2024E | D3: 2025E | E3: 2026E | F3: 2027E | G3: 2028E
A4: Revenue | B4: ='Operating Projections'!B4 -> 20426 | C4: ='Operating Projections'!C4 -> 21406.448 | D4: ='Operating Projections'!D4 -> 22433.958 | E4: ='Operating Projections'!E4 -> 23510.787 | F4: ='Operating Projections'!F4 -> 24545.262 | G4: ='Operating Projections'!G4 -> 25527.073
A5: EBITDA | B5: ='Operating Projections'!B6 -> 5891 | C5: ='Operating Projections'!C6 -> 5993.8054 | D5: ='Operating Projections'!D6 -> 6326.376 | E5: ='Operating Projections'!E6 -> 6677.0636 | F5: ='Operating Projections'!F6 -> 6995.3997 | G5: ='Operating Projections'!G6 -> 7275.2157
A6: EBIT | B6: =B5-B11 -> 3848.4 | C6: =C5-C11 -> 3853.1606 | D6: =D5-D11 -> 4082.9803 | E6: =E5-E11 -> 4325.9849 | F6: =F5-F11 -> 4540.8735 | G6: =G5-G11 -> 4722.5084
A7: Cash Tax Rate (%) | B7: 0.24 | C7: 0.24 | D7: 0.24 | E7: 0.24 | F7: 0.24 | G7: 0.24
A8: Cash Taxes | B8: =B7*B6 -> 923.616 | C8: =C7*C6 -> 924.75855 | D8: =D7*D6 -> 979.91526 | E8: =E7*E6 -> 1038.2364 | F8: =F7*F6 -> 1089.8096 | G8: =G7*G6 -> 1133.402
A9: NOPAT | B9: =B6-B8 -> 2924.784 | C9: =C6-C8 -> 2928.4021 | D9: =D6-D8 -> 3103.065 | E9: =E6-E8 -> 3287.7485 | F9: =F6-F8 -> 3451.0639 | G9: =G6-G8 -> 3589.1064
A10: D&A (% of Revenue) | B10: 0.1 | C10: 0.1 | D10: 0.1 | E10: 0.1 | F10: 0.1 | G10: 0.1
A11: Depreciation & Amortization | B11: =B10*B4 -> 2042.6 | C11: =C10*C4 -> 2140.6448 | D11: =D10*D4 -> 2243.3958 | E11: =E10*E4 -> 2351.0787 | F11: =F10*F4 -> 2454.5262 | G11: =G10*G4 -> 2552.7073
A12: CapEx (% of Revenue) | B12: 0.14 | C12: 0.14 | D12: 0.138 | E12: 0.135 | F12: 0.135 | G12: 0.135
A13: Capital Expenditures | B13: =B12*B4 -> 2859.64 | C13: =C12*C4 -> 2996.9027 | D13: =D12*D4 -> 3095.8861 | E13: =E12*E4 -> 3173.9563 | F13: =F12*F4 -> 3313.6104 | G13: =G12*G4 -> 3446.1548
A14: Change in NWC (% of Revenue) | B14: 0.005 | C14: 0.005 | D14: 0.005 | E14: 0.005 | F14: 0.005 | G14: 0.005
A15: Change in Net Working Capital | C15: 107.03224 | D15: 112.16979 | E15: 117.55394 | F15: 98.181048 | G15: 102.10829
A16: Unlevered Free Cash Flow | B16: =B9+B11-B13-B15 -> 2107.744 | C16: =C6-C8+C11-C13-C15 -> 1965.1119 | D16: =D6-D8+D11-D13-D15 -> 2138.4048 | E16: =E6-E8+E11-E13-E15 -> 2347.317 | F16: =F6-F8+F11-F13-F15 -> 2493.7986 | G16: =G6-G8+G11-G13-G15 -> 2593.5506
A19: Cash Flow Matrix
A21: UFCF CGAR | B21: 0.046
A22: Avg UFCF Margin | B22: 0.14
A23: Cash Conversion | B23: 0.5

Sheet DCF Valuation
A3: WAAC | B3: 0.0655
A4: Terminal Growth Rate | B4: 0.0225
A5: Valuation Method | B5: Prepetuity Growth
A11: Unleveraged Free Cash Flow
A12: UFCF | B12: 2024E | C12: 2025E | D12: 2026E | E12: 2027E | F12: 2028E | G12: Total PV
B13: ='Unleveraged Cash Flow'!C16 -> 1965.1119 | C13: ='Unleveraged Cash Flow'!D16 -> 2138.4048 | D13: ='Unleveraged Cash Flow'!E16 -> 2347.317 | E13: ='Unleveraged Cash Flow'!F16 -> 2493.7986 | F13: ='Unleveraged Cash Flow'!G16 -> 2593.5506 | G13: =SUM(B13:F13) -> 11538.183
A16: Year | B16: 1 | C16: 2 | D16: 3 | E16: 4 | F16: 5
A17: Discount Factor | B17: =1/(1+B3)^B16 -> 0.93852651 | C17: =1/(1+B3)^C16 -> 0.88083202 | D17: =1/(1+B3)^D16 -> 0.8266842 | E17: =1/(1+B3)^E16 -> 0.77586504 | F17: =1/(1+B3)^F16 -> 0.72816991
A19: Present Value of Future Cash Flow
B20: 2024E | C20: 2025E | D20: 2026E | E20: 2027E | F20: 2028E | G20: Total PV
A21: UFCF | B21: =B13 -> 1965.1119 | C21: =C13 -> 2138.4048 | D21: =D13 -> 2347.317 | E21: =E13 -> 2493.7986 | F21: 2593.6
A22: Disount Factor | B22: =B17 -> 0.93852651 | C22: =C17 -> 0.88083202 | D22: =D17 -> 0.8266842 | E22: =E17 -> 0.77586504 | F22: =F17 -> 0.72816991
A23: PV of FCF | B23: =B22*B21 -> 1844.3096 | C23: =C22*C21 -> 1883.5754 | D23: =D22*D21 -> 1940.4899 | E23: =E22*E21 -> 1934.8512 | F23: =F22*F21 -> 1888.5815 | G23: =SUM(B23:F23) -> 9491.8076
A26: UFCF Year 2028 E | B26: 2593.6
A27: Terminal Growth Rate | B27: =B4 -> 0.0225
A28: WAAC | B28: 0.0654925
A29: Termianal Value | B29: 58968.324
A33: Present Value of Termianl Value
A34: Terminal Value | B34: =B29 -> 58968.324
A35: Discount Factor | B35: 0.7237
A36: PV of Termianal Value | B36: 42940.471
A39: Enterprise Value Build
A40: PV of UFCF (Year 2024-2028) | B40: =G23 -> 9491.8076
A41: PV of Terminal Value | B41: =B36 -> 42940.471
A42: Enterprise Value | B42: =B41+B40 -> 52432.279
A47: Equity Value Bridge
A48: Enterprise Value | B48: =B42 -> 52432.279
A49: Net Debt | B49: 16200
A50: Equity Value | B50: =B48-B49 -> 36232.279
A53: Implied Share Value
A54: Equity Value | B54: =B50 -> 36232.279
A55: Diluted shares | B55: 407
A56: DCF value/ share | B56: =B54/B55 -> 89.022797

Sheet DCF Sensitivities
A1: Sensitivities
A6: WACC \ g | B6: 0.0175 | C6: 2.25% (Base) | D6: 0.0275
A7: 0.0555 | B7: 113.6 | C7: 128.9 | D7: 149.8
A8: 6.55% (Base) | B8: 78.9 | C8: 89 | D8: 103
A9: 0.0755 | B9: 60.3 | C9: 67.9 | D9: 78.6
A11: The $30.30 cash offer represents a conservative, risk-adjusted entry price relative to standalone valuation benchmarks

Sheet Trading and Trsaction Valuation
A3: Metrics | B3: EV/ EBITDA
A4: Trading Comps | B4: 8.6 x
A5: 25th Percentile | B5: 9.3 x
A6: Median | B6: 10.1 x
A7: 75th Percentile
A10: WM LTM EBITDA | B10: 12345.9
A15: Precedent Trasactions
A16: Metrics | B16: EV / EBITDA
A17: Low | B17: 9.0 x
A18: Median | B18: 9.8 x
A19: High | B19: 10.5 x
A20: Implied Valuation Range
A23: Net Debt | B23: 16200
A24: Diluted Shares | B24: 407
A28: Valuation Method | B28: Low | C28: Median | D28: High
A29: Trading Comps | B29: 187.4 | C29: 219.9 | D29: 252.3
A30: Precedent Transactions | B30: 205.8 | C30: 236.7 | D30: 271.4
A33: Public market multiples imply a premium valuation relative to intrinsic DCF, reflecting WM’s stable, infrastructure-like cash flows.
A34: Precedent transactions further support higher control valuations, consistent with scarcity value and defensive end-market exposure.

Sheet Trading Comp - Appendix
A2: Company | B2: Enterprise Value ($mm) | C2: LTM EBITDA ($mm) | D2: EV / EBITDA
A3: Waste Connections | B3: 18450 | C3: 2120 | D3: 8.7x
A4: Republic Services | B4: 36800 | C4: 4020 | D4: 9.2x
A5: GFL Environmental | B5: 15600 | C5: 1720 | D5: 9.1x
A6: Clean Harbors | B6: 13900 | C6: 1350 | D6: 10.3x
A7: Casella Waste Systems | B7: 4850 | C7: 480 | D7: 10.1x
A10: Statistic | B10: EV / EBITDA
A11: 25th Percentile | B11: 8.6x
A12: Median | B12: 9.3x
A13: 75th Percentile | B13: 10.1x
A15: Note: Financial data based on latest available LTM public filings.

Sheet Trading Comp Implied Valuation-
A2: Input | B2: Value
A3: Advanced Disposal LTM EBITDA | B3: $1,030 mm
A4: Net Debt | B4: $3,200 mm
A5: Diluted Shares Outstanding | B5: 110 mm
A8: Implied Valuation- Trading Comps
A10: Case | B10: EV / EBITDA | C10: Implied Enterprise Value ($mm)
A11: Low | B11: 8.6x | C11: 8858
A12: Median | B12: 9.3x | C12: 9579
A13: High | B13: 10.1x | C13: 10403
A16: Equity Value Bridge
A18: Case | B18: Low | C18: Median | D18: High
A19: Implied Enterprise Value | B19: 8858 | C19: 9579 | D19: 10403
A20: Less: Net Debt | B20: -3200 | C20: -3200 | D20: -3200
A21: Implied Equity Value | B21: 5658 | C21: 6379 | D21: 7203
A22: Implied Equity Value per Share
A27: Case | B27: Equity Value ($mm) | C27: Shares (mm) | D27: Value / Share
A28: Low | B28: 5658 | C28: 110 | D28: 51.4
A29: Median | B29: 6379 | C29: 110 | D29: 58
A30: High | B30: 7203 | C30: 110 | D30: 65.5

Sheet Precedent Transactions - Append
A3: Acquirer | B3: Target | C3: Announcement Year | D3: Deal EV ($mm) | E3: LTM EBITDA ($mm) | F3: EV / EBITDA
A4: Waste Connections | B4: Progressive Waste | C4: 2016 | D4: 4900 | E4: 540 | F4: 9.1x
A5: Republic Services | B5: US Ecology | C5: 2022 | D5: 2200 | E5: 240 | F5: 9.2x
A6: GFL Environmental | B6: WCA Waste | C6: 2021 | D6: 1850 | E6: 195 | F6: 9.5x
A7: Waste Management | B7: Advanced Disposal | C7: 2020 | D7: 4600 | E7: 470 | F7: 9.8x
A8: Clean Harbors | B8: Environmental Services Unit | C8: 2019 | D8: 1150 | E8: 110 | F8: 10.5x
A12: Trasaction Multiple Statistics
A14: Statistic | B14: EV / EBITDA
A15: Low | B15: 9.0x
A16: Median | B16: 9.8x
A17: High | B17: 10.5x
A19: Note: Transaction multiples based on publicly disclosed deal values and LTM EBITDA at announcement.

Sheet Precendent Transactions Implied
A2: Key Inputs
A4: Input | B4: Value
A5: Advanced Disposal LTM EBITDA | B5: $1,030 mm
A6: Net Debt | B6: $3,200 mm
A7: Diluted Shares Outstanding | B7: 110 mm
A11: Implied Enterprise Value- Precedent Transactions
A13: Case | B13: EV / EBITDA | C13: Implied Enterprise Value ($mm)
A14: Low | B14: 9.0x | C14: 9270
A15: Median | B15: 9.8x | C15: 10094
A16: High | B16: 10.5x | C16: 10815
A21: Equity Value Bridge
A23: Case | B23: Low | C23: Median | D23: High
A24: Implied Enterprise Value | B24: 9270 | C24: 10094 | D24: 10815
A25: Less: Net Debt | B25: -3200 | C25: -3200 | D25: -3200
A26: Implied Equity Value | B26: 6070 | C26: 6894 | D26: 7615
A30: Implied Value Per Share
A32: Case | B32: Equity Value ($mm) | C32: Shares (mm) | D32: Value / Share
A33: Low | B33: 6070 | C33: 110 | D33: 55.2
A34: Median | B34: 6894 | C34: 110 | D34: 62.7
A35: High | B35: 7615 | C35: 110 | D35: 69.2
