Workbook

Sheet Trasaction Overview 
A3: Trasaction Type | B3: Sponsor Buyout
A5: Sponsor | B5: Thoma Bravo
A6: Target | B6: Proof Point Inc.
A7: Deal Type | B7: Take Private LBO
A8: Deal Year | B8: 2021
A9: Projections | B9: 2022-2026
A10: Cureency | B10: USD(mm)
A11: Hold period | B11: 5 years
A13: LTM Operating model
A15: LTM Revenue | B15: 1050 | D15: Value Creation Levers:
A16: LTM EBITDA | B16: 315 | D16: • Revenue growth driven by cybersecurity demand
A17: EBITDA Margin | B17: =B16/B15 -> 0.3 | D17: • EBITDA margin expansion via operating leverage
D18: • Rapid deleveraging through strong FCF
D19: • Stable exit multiple (no expansion assumed)
A20: Target IRR | B20: 0.25
A21: Target MOIC | B21: 0.033
A22: Entry Valuations
A24: Entry EBITDA Multiple | B24: 9
A25: Enterprise Value | B25: =B24*B16 -> 2835
A26: Net Debt Assumed | B26: 0
A27: Equity Purchase Price | B27: =B25-B26 -> 2835
A28: Equity Contribution | B28: 1332.5
A30: Financing Mix
A32: Debt | B32: 0.6
A33: Equity | B33: 0.4
A36: Outputs
A37: Total Debt | B37: =B32*B27 -> 1701
A38: Total Equity | B38: =B33*B27 -> 1134

Sheet Operating Assumptions
A1: Operating Assumptions
A3: Metrics | B3: LTM Base Year | C3: 2022E | D3: 2023E | E3: 20245E | F3: 2025E | G3: 2026E
A4: Revenue Growth Rate | C4: 0.09 | D4: 0.09 | E4: 0.085 | F4: 0.08 | G4: 0.075
A5: Revenue | B5: ='Trasaction Overview '!B15 -> 1050 | C5: =C4*B5+B5 -> 1144.5 | D5: =D4*C5+C5 -> 1247.505 | E5: =E4*D5+D5 -> 1353.5429 | F5: =F4*E5+E5 -> 1461.8264 | G5: =G4*F5+F5 -> 1571.4633
A6: EBITDA Margin Growth | C6: 0.31 | D6: 0.32 | E6: 0.33 | F6: 0.34 | G6: 0.35
A7: EBITDA | B7: ='Trasaction Overview '!B16 -> 315 | C7: =C6*C5 -> 354.795 | D7: =D6*D5 -> 399.2016 | E7: =E6*E5 -> 446.66917 | F7: =F6*F5 -> 497.02096 | G7: =G6*G5 -> 550.01217
A9: CapEx (% of Revenue) | C9: 0.015 | D9: 0.015 | E9: 0.015 | F9: 0.015 | G9: 0.015
A10: CapEx (% of Revenue) | C10: =C9*C5 -> 17.1675 | D10: =D9*D5 -> 18.712575 | E10: =E9*E5 -> 20.303144 | F10: =F9*F5 -> 21.927395 | G10: =G9*G5 -> 23.57195
A12: Cash Tax Rate | C12: 0.25 | D12: 0.25 | E12: 0.25 | F12: 0.25 | G12: 0.25
A14: Change in NWC | C14: 0 | D14: 0 | E14: 0 | F14: 0 | G14: 0
A17: Mertics | B17: Values | C17: Ratioale
A18: Revenue Growth CGAR | B18: Reduced by 1.5 % | C18: Assumes continued enterprise cybersecurity spend and customer retention
A19: EBITDA Grwoth CGAR | B19: 31% - 35% | C19: Margin expansion driven by scale efficiencies and cost discipline
A20: Capex | B20: 0.015
A21: Change in Nwc | B21: 0
A22: Cash Tax Rate | B22: 0.25

Sheet Operational Multiples
A2: Metrics | B2: LTM 2021 | C2: 2022E | D2: 2023E | E2: 2024E | F2: 2025E | G2: 2026E
A3: Revenue | B3: 1050 | C3: =C4*B3+B3 -> 1144.5 | D3: =D4*C3+C3 -> 1247.505 | E3: =E4*D3+D3 -> 1353.5429 | F3: =F4*E3+E3 -> 1461.8264 | G3: =G4*F3+F3 -> 1571.4633
A4: Revenue Growth | C4: 0.09 | D4: 0.09 | E4: 0.085 | F4: 0.08 | G4: 0.075
A5: EBITDA | B5: 315 | C5: =C6*C3 -> 354.795 | D5: =D6*D3 -> 399.2016 | E5: =E6*E3 -> 446.66917 | F5: =F6*F3 -> 497.02096 | G5: =G6*G3 -> 550.01217
A6: EBITDA Margin | C6: ='Operating Assumptions'!C6 -> 0.31 | D6: ='Operating Assumptions'!D6 -> 0.32 | E6: ='Operating Assumptions'!E6 -> 0.33 | F6: ='Operating Assumptions'!F6 -> 0.34 | G6: ='Operating Assumptions'!G6 -> 0.35
A7: CapEx | C7: =C8*C3 -> 17.1675 | D7: =D8*D3 -> 18.712575 | E7: =E8*E3 -> 20.303144 | F7: =F8*F3 -> 21.927395 | G7: =G8*G3 -> 23.57195
A8: CapEx(% Of Revenue) | C8: ='Operating Assumptions'!C9 -> 0.015 | D8: ='Operating Assumptions'!D9 -> 0.015 | E8: ='Operating Assumptions'!E9 -> 0.015 | F8: ='Operating Assumptions'!F9 -> 0.015 | G8: ='Operating Assumptions'!G9 -> 0.015
A9: Cash Tax Rate | C9: =C10*C5 -> 88.69875 | D9: =D10*D5 -> 99.8004 | E9: =E10*E5 -> 111.66729 | F9: =F10*F5 -> 124.25524 | G9: =G10*G5 -> 137.50304
A10: Cash Tax Rate (% of Revenue) | C10: ='Operating Assumptions'!C12 -> 0.25 | D10: ='Operating Assumptions'!D12 -> 0.25 | E10: ='Operating Assumptions'!E12 -> 0.25 | F10: ='Operating Assumptions'!F12 -> 0.25 | G10: ='Operating Assumptions'!G12 -> 0.25
A11: Free Cash Flow | C11: =C5-C7-C9 -> 248.92875 | D11: =D5-D7-D9 -> 280.68863 | E11: =E5-E7-E9 -> 314.69873 | F11: =F5-F7-F9 -> 350.83833 | G11: =G5-G7-G9 -> 388.93718
A13: Multiple Commentary:
A14: • Entry multiple in line with large-cap cybersecurity transactions
A15: • Exit multiple assumes no expansion relative to entry
A17: Summary
A19: Entry EBITDA | B19: 315
A20: Entry EV | B20: 2891.7
A21: Entry EV / EBITDA | B21: 9.0x
A22: Exit EBITDA (2026E) | B22: 550
A23: Exit EV | B23: 4400.1
A24: Exit EV / EBITDA | B24: 8.0x

Sheet Sources and Uses
A3: Purchase of Equity | B3: ='Trasaction Overview '!B27 -> 2835 | D3: Entry Leverage Metrics | E3: Values
A4: Transaction Fees | B4: =B5*B3 -> 56.7 | D4: Total Debt/ EBITDA | E4: 4.95 x
A5: Trasaction Fees (% of EV) | B5: 0.02 | D5: Debt / Enterprise | E5: 0.539
A6: Total Uses | B6: =B3+B4 -> 2891.7 | D6: Equity Contribution | E6: 0.461
A9: Sources Of fund
A10: Term Loan B | B10: ='Trasaction Overview '!B33*'Trasaction Overview '!B25 -> 1134
A11: Subordinated Notes | B11: =0.15*B3 -> 425.25
A12: Total Debt | B12: =B10+B11 -> 1559.25
A13: Sponsor Equity | B13: =B6-B12 -> 1332.45
A14: Total Sources | B14: =SUM(B10,B11,B13) -> 2891.7

Sheet  Incremental Revenue and EBITDA
A2: Metrics | B2: 2021A | C2: 2022E | D2: 2023E | E2: 2024E | F2: 2025E | G2: 2026E
A3: Beginning Revenue | B3: ='Trasaction Overview '!B15 -> 1050 | C3: =B6 -> 1050 | D3: =C6 -> 1144.5 | E3: =D6 -> 1247.505 | F3: =E6 -> 1353.5429 | G3: =F6 -> 1461.8264
A4: Organic Grtoqth Percentage | C4: 0.09 | D4: 0.09 | E4: 0.085 | F4: 0.08 | G4: 0.075
A5: Incremental Revenue | C5: =C4*C3 -> 94.5 | D5: =D4*D3 -> 103.005 | E5: =E4*E3 -> 106.03793 | F5: =F4*F3 -> 108.28343 | G5: =G4*G3 -> 109.63698
A6: Ending Revenue | B6: =B3 -> 1050 | C6: =C4*C3+C3 -> 1144.5 | D6: =D4*D3+D3 -> 1247.505 | E6: =E4*E3+E3 -> 1353.5429 | F6: =F4*F3+F3 -> 1461.8264 | G6: =G4*G3+G3 -> 1571.4633
A8: Metrics | B8: 2021A | C8: 2022E | D8: 2023E | E8: 2024E | F8: 2025E | G8: 2026E
A9: Ending Revnue | B9: =' Incremental Revenue and EBITDA'!B6 -> 1050 | C9: =' Incremental Revenue and EBITDA'!C6 -> 1144.5 | D9: =' Incremental Revenue and EBITDA'!D6 -> 1247.505 | E9: =' Incremental Revenue and EBITDA'!E6 -> 1353.5429 | F9: =' Incremental Revenue and EBITDA'!F6 -> 1461.8264 | G9: =' Incremental Revenue and EBITDA'!G6 -> 1571.4633
A10: EBITDA Margin% | B10: 0.3 | C10: 0.31 | D10: 0.32 | E10: 0.33 | F10: 0.34 | G10: 0.35 | I10: EBITDA expansion reflects operating leverage and disciplined cost management.
A11: EBITDA | B11: =B10*B9 -> 315 | C11: =C10*C9 -> 354.795 | D11: =D10*D9 -> 399.2016 | E11: =E10*E9 -> 446.66917 | F11: =F10*F9 -> 497.02096 | G11: =G10*G9 -> 550.01217

Sheet Free Cash Flow & EBITDA 
A2: Metrics | B2: 2021A | C2: 2022E | D2: 2023E | E2: 2024E | F2: 2025E | G2: 2026E
A3: EBITDA | B3: =' Incremental Revenue and EBITDA'!B11 -> 315 | C3: =' Incremental Revenue and EBITDA'!C11 -> 354.795 | D3: =' Incremental Revenue and EBITDA'!D11 -> 399.2016 | E3: =' Incremental Revenue and EBITDA'!E11 -> 446.66917 | F3: =' Incremental Revenue and EBITDA'!F11 -> 497.02096 | G3: =' Incremental Revenue and EBITDA'!G11 -> 550.01217
A4: Cash Taxes | C4: ='Operational Multiples'!C9 -> 88.69875 | D4: ='Operational Multiples'!D9 -> 99.8004 | E4: ='Operational Multiples'!E9 -> 111.66729 | F4: ='Operational Multiples'!F9 -> 124.25524 | G4: ='Operational Multiples'!G9 -> 137.50304
A5: Capex | C5: ='Operating Assumptions'!C10 -> 17.1675 | D5: ='Operating Assumptions'!D10 -> 18.712575 | E5: ='Operating Assumptions'!E10 -> 20.303144 | F5: ='Operating Assumptions'!F10 -> 21.927395 | G5: ='Operating Assumptions'!G10 -> 23.57195
A6: Change in NWC | C6: 0 | D6: 0 | E6: 0 | F6: 0 | G6: 0
A7: Free Cash Flow | C7: =C3-C4-C5-C6 -> 248.92875 | D7: =D3-D4-D5-D6 -> 280.68863 | E7: =E3-E4-E5-E6 -> 314.69873 | F7: =F3-F4-F5-F6 -> 350.83833 | G7: =G3-G4-G5-G6 -> 388.93718 | I7: Cash flow excludes discretionary acquisitions and assumes steady-state working capital.

Sheet Debt Schedule and Cash Sweeep
A2: Mertrics | B2: 2021A | C2: 2022E First full Year after Post- Close | D2: 2023E | E2: 2024E | F2: 2025E | G2: 2026E
A3: Opening Balance | B3: ='Sources and Uses'!B10 -> 1134 | C3: =B9 -> 1134 | D3: =C9 -> 885.07125 | E3: =D9 -> 604.38262 | F3: =E9 -> 289.68389 | G3: =F9 -> -0.033105063
A4: Mandatory Ammortization. | C4: =C5*'Sources and Uses'!B14 -> 28.917 | D4: ='Sources and Uses'!B14*C5 -> 28.917 | E4: 28.917 | F4: 28.917 | G4: 0
A5: Mandatory Ammortization(%) | C5: 0.01 | D5: 0.01 | E5: 0.01 | F5: 0.01 | G5: 0.01
A6: Remaning after Ammortization | C6: =C3-C4 -> 1105.083 | D6: =D3-D4 -> 856.15425 | E6: =E3-E4 -> 575.46562 | F6: =F3-F4 -> 260.76689 | G6: =G3-G4 -> -0.033105063
A7: Optional Cash Sweep | C7: =MIN('Free Cash Flow & EBITDA '!C7-C4) -> 220.01175 | D7: =MIN('Free Cash Flow & EBITDA '!D7-D4) -> 251.77163 | E7: =MIN('Free Cash Flow & EBITDA '!E7-E4) -> 285.78173 | F7: 260.8 | G7: 0
A8: Total Pricipal Repayment | C8: =C4+C7 -> 248.92875 | D8: =D4+D7 -> 280.68863 | E8: =E4+E7 -> 314.69873 | F8: =F4+F7 -> 289.717 | G8: =G4+G7 -> 0
A9: Ending balance | B9: 1134 | C9: =C3-C8 -> 885.07125 | D9: =D3-D8 -> 604.38262 | E9: =E3-E8 -> 289.68389 | F9: =F3-F8 -> -0.033105063 | G9: =G3-G8 -> -0.033105063
A11: No covenant breaches assumed throughout projection period.

Sheet Exit Analysis
A3: Exit Year | B3: 2026E
A4: Exit EBITDA Multiple | B4: 8
A5: 2026 Exit EBITDA | B5: =' Incremental Revenue and EBITDA'!G11 -> 550.01217
A6: Exit Enterprise Value | B6: =B5*B4 -> 4400.0973
A7: Exit Debt | B7: ='Debt Schedule and Cash Sweeep'!G9 -> -0.033105063
A8: Exit Cash | B8: ='Debt Schedule and Cash Sweeep'!G7 -> 0
A9: Exit Equity Value | B9: =B6-B7 -> 4400.1304
A11: Scenario | B11: Exit Multiple | C11: Exit EV
A12: Low | B12: 7.5x | C12: 4125.1
A13: Base | B13: 8.0x | C13: 4400.1
A14: High | B14: 8.5x | C14: 4675.1
A16: Final Thoughts: | B16: I calculate exit equity value by applying an exit multiple to final-year EBITDA and subtracting net debt outstanding at exit.
B17: Exit assumes stable trading environment with no multiple expansion.

Sheet Returns
A2: Metrics | B2: 2021A | C2: 2022E | D2: 2023E | E2: 2024E | F2: 2025E | G2: 2026E
A3: Equity Contributions | B3: ='Sources and Uses'!B13 -> 1332.45 | C3: 0 | D3: 0 | E3: 0 | F3: 0 | G3: 0
A4: Dividents/ Distributions | B4: 0 | C4: 0 | D4: 0 | E4: 0 | F4: 0 | G4: 0
A5: Exit Equity Proceeds | B5: 0 | C5: 0 | D5: 0 | E5: 0 | F5: 0 | G5: ='Exit Analysis'!B9 -> 4400.1304
A6: Net Equity Cash Flow | B6: {=SUM(-B3:B5)} -> -1332.45 | C6: =SUM(C3:C5) -> 0 | D6: =SUM(D3:D5) -> 0 | E6: =SUM(E3:E5) -> 0 | F6: =SUM(F3:F5) -> 0 | G6: =SUM(G3:G5) -> 4400.1304
A8: IRR | B8: =IRR(B6:G6) -> 0.26988071
A10: MOIC | B10: =G6/B3 -> 3.3022856
A13: Sensitivity Senario
A14: Exit Multiples | B14: IRR | C14: MoIC
A15: 8.5X | B15: 0.29 | C15: 3.5
A16: 8.0X | B16: 0.27 | C16: 3.33 | F16: 28
A17: 7.5X | B17: 0.25 | C17: 3.09
A18: 7.0X | B18: 0.24 | C18: 2.89
A21: Final Thoughts | B21: Even at a 7.0× exit multiple, the deal generates ~24% IRR and ~2.9× MoIC, which indicates that value creation is driven by operational improvements and deleveraging rather than multiple expansion.
